hikvision_isapi/__init__.py
hikvision_isapi/client.py
hikvision_isapi_py-1.1.1.dist-info/LICENSE
hikvision_isapi_py-1.1.1.dist-info/METADATA
hikvision_isapi_py-1.1.1.dist-info/WHEEL
hikvision_isapi_py-1.1.1.dist-info/top_level.txt
hikvision_isapi_py-1.1.1.dist-info/RECORD
