Metadata-Version: 2.1
Name: hikvision-isapi-py
Version: 1.1.1
Summary: HIKVision ISAPI python library
Requires-Python: >=3.8
License-File: LICENSE
Requires-Dist: requests
Provides-Extra: dev
Requires-Dist: black ; extra == 'dev'
Requires-Dist: build ; extra == 'dev'
Requires-Dist: flake8 ; extra == 'dev'
Requires-Dist: isort ; extra == 'dev'
Requires-Dist: tbump ; extra == 'dev'
